{
  "id": "RBI-2026-06-10-rbi-consolidates-rul",
  "title": "RBI Consolidates Rules on Pre-2005 Banknotes Due to Security Upgrade Measures",
  "date": "2026-06-10",
  "source_url": "https://taxguru.in/rbi/rbi-consolidates-rules-pre-2005-banknotes-due-security-upgrade-measures.html",
  "feed_type": "aggregator",
  "description": "RBI has reiterated that old series banknotes issued before 2005 remain legal tender but should not be re-issued by banks. The circular consolidates earlier instructions aimed at introducing notes with enhanced security features.\nThe post RBI Consolidates Rules on Pre-2005 Banknotes Due to Security Upgrade Measures appeared first on TaxGuru.",
  "generated": "2026-06-10T07:05:32.920194+00:00"
}