{
  "id": "RBI-2026-06-18-rbi-rural-co-operati",
  "title": "RBI (Rural Co-operative Banks \u2013 Interest Rate on Deposits) Amendment Directions, 2026",
  "date": "2026-06-18",
  "source_url": "https://taxguru.in/rbi/rbi-rural-co-operative-banks-interest-rate-deposits-amendment-directions-2026.html",
  "feed_type": "aggregator",
  "description": "RBI has removed the interest rate ceiling on fresh FCNR(B) deposits with tenors of three to five years until September 30, 2026. The relaxation also applies to deposits renewed upon maturity during the specified period.\nThe post RBI (Rural Co-operative Banks \u2013 Interest Rate on Deposits) Amendment Directions, 2026 appeared first on TaxGuru.",
  "generated": "2026-06-18T08:04:01.781272+00:00"
}